MPSENet/__init__.py
MPSENet/env.py
MPSENet/model/__init__.py
MPSENet/model/mpsenet.py
MPSENet/model/transformer.py
mpsenet-1.0.3.dist-info/METADATA
mpsenet-1.0.3.dist-info/WHEEL
mpsenet-1.0.3.dist-info/licenses/LICENSE
mpsenet-1.0.3.dist-info/RECORD
