Metadata-Version: 2.3
Name: MPSENet
Version: 1.0.3
Summary: Python package of MP-SENet from Explicit Estimation of Magnitude and Phase Spectra in Parallel for High-Quality Speech Enhancement.
Project-URL: Homepage, https://github.com/jacoblincool/MPSENet
Project-URL: Issues, https://github.com/jacoblincool/MPSENet/issues
Author: yxlu-0102
License-Expression: MIT
License-File: LICENSE
Requires-Python: >=3.10
Requires-Dist: einops
Requires-Dist: huggingface-hub
Requires-Dist: joblib
Requires-Dist: librosa
Requires-Dist: numpy
Requires-Dist: soundfile
Requires-Dist: torch
